cognitive/__init__.py
cognitive/cli.py
cognitive/loader.py
cognitive/registry.py
cognitive/runner.py
cognitive/subagent.py
cognitive/templates.py
cognitive/validator.py
cognitive/providers/__init__.py
cognitive_modules-0.4.0.dist-info/licenses/LICENSE
cognitive_modules-0.4.0.dist-info/METADATA
cognitive_modules-0.4.0.dist-info/WHEEL
cognitive_modules-0.4.0.dist-info/entry_points.txt
cognitive_modules-0.4.0.dist-info/top_level.txt
cognitive_modules-0.4.0.dist-info/RECORD
