Metadata-Version: 2.4
Name: cognitive-modules
Version: 0.4.0
Summary: Structured LLM task runner with schema validation, confidence scoring, and subagent orchestration
Author: ziel-io
License: MIT
Project-URL: Homepage, https://github.com/ziel-io/cognitive-modules
Project-URL: Documentation, https://github.com/ziel-io/cognitive-modules#readme
Project-URL: Repository, https://github.com/ziel-io/cognitive-modules
Project-URL: Issues, https://github.com/ziel-io/cognitive-modules/issues
Keywords: llm,cognitive,modules,ai,cli,schema,validation,prompt,agent,subagent
Classifier: Development Status :: 4 - Beta
Classifier: Intended Audience :: Developers
Classifier: License :: OSI Approved :: MIT License
Classifier: Operating System :: OS Independent
Classifier: Programming Language :: Python :: 3
Classifier: Programming Language :: Python :: 3.9
Classifier: Programming Language :: Python :: 3.10
Classifier: Programming Language :: Python :: 3.11
Classifier: Programming Language :: Python :: 3.12
Classifier: Topic :: Software Development :: Libraries :: Python Modules
Classifier: Topic :: Scientific/Engineering :: Artificial Intelligence
Requires-Python: >=3.9
License-File: LICENSE
Requires-Dist: jsonschema>=4.17.0
Requires-Dist: pyyaml>=6.0
Requires-Dist: typer>=0.9.0
Requires-Dist: rich>=13.0.0
Provides-Extra: openai
Requires-Dist: openai>=1.0.0; extra == "openai"
Provides-Extra: anthropic
Requires-Dist: anthropic>=0.18.0; extra == "anthropic"
Provides-Extra: ollama
Requires-Dist: requests>=2.28.0; extra == "ollama"
Provides-Extra: minimax
Requires-Dist: openai>=1.0.0; extra == "minimax"
Provides-Extra: all
Requires-Dist: openai>=1.0.0; extra == "all"
Requires-Dist: anthropic>=0.18.0; extra == "all"
Requires-Dist: requests>=2.28.0; extra == "all"
Provides-Extra: dev
Requires-Dist: pytest>=7.0.0; extra == "dev"
Requires-Dist: pytest-cov>=4.0.0; extra == "dev"
Requires-Dist: build>=1.0.0; extra == "dev"
Requires-Dist: twine>=4.0.0; extra == "dev"
Requires-Dist: ruff>=0.1.0; extra == "dev"
Provides-Extra: docs
Requires-Dist: mkdocs-material>=9.0.0; extra == "docs"
Requires-Dist: pymdown-extensions>=10.0.0; extra == "docs"
Dynamic: license-file
